{
  "leader_count": 5,
  "special_count": 21,
  "squad_count": 54,
  "total_count": 80,
  "name": "Нильфгаард",
  "leader": [
    {
      "name": "Эмгыр вар Эмрейс",
      "description": "Меч - лишь одно из орудий в распоряжении имератора.",
      "type": "Карта лидера",
      "abilities": "Отменяет эффект умения вражеского лидера",
      "fraction": "Нильфгаард",
      "count": 1
    },
    {
      "name": "Эмгыр вар Эмрейс Император Нильфгаарда",
      "description": "Мотивы меня не интересуют. Только результаты.",
      "type": "Карта лидера",
      "abilities": "Посмотрите три случайные карты из руки противника",
      "fraction": "Нильфгаард",
      "count": 1
    },
    {
      "name": "Эмгыр вар Эмрейс Йож из Эрленвальда",
      "description": "Интересно, как себя чувствует человек, прикончивший собственную жену?",
      "type": "Карта лидера",
      "abilities": "Возьмите из вашей колоды Ливень и сыграйте эту карту немедленно",
      "fraction": "Нильфгаард",
      "count": 1
    },
    {
      "name": "Эмгыр вар Эмрейс Завоеватель Севера",
      "description": "Императоры владеют империями, но двумя вещами владеть не могут: своим сердцем и своим временем.",
      "type": "Карта лидера",
      "abilities": "Умения, воскрешающие отряд, восстанавливают случайно выбранный отряд. Карта действует на обоих игроков",
      "fraction": "Нильфгаард",
      "count": 1
    },
    {
      "name": "Эмгыр вар Эмрейс Завоеватель Юга",
      "description": "Император не славится терпением. Он хочет видеть свою дочь. Как можно скорее.",
      "type": "Карта лидера",
      "abilities": "Возьмите карту из отбоя вашего соперника",
      "fraction": "Нильфгаард",
      "count": 1
    }
  ],
  "special": [
    {
      "name": "Казнь",
      "description": "Огненные столпы обращают величайших в пепел. Остальные благоговейно трепещут.",
      "type": "Специальная карта",
      "abilities": "Казнь",
      "fraction": "Общий",
      "count": 3
    },
    {
      "name": "Командирский рог",
      "description": "Плюс один к морали, минус три к слуху",
      "type": "Специальная карта",
      "abilities": "Командирский рог",
      "fraction": "Общий",
      "count": 3
    },
    {
      "name": "Ливень",
      "description": "В этом краю даже дождь смердит мочой",
      "type": "Специальная карта",
      "abilities": "Ливень",
      "fraction": "Общий",
      "count": 3
    },
    {
      "name": "Мгла",
      "description": "Вот туман-то... хоть глаз выколи",
      "type": "Специальная карта",
      "abilities": "Мгла",
      "fraction": "Общий",
      "count": 3
    },
    {
      "name": "Мороз",
      "description": "Мечта хорошего коммандира... кошмар плохого.",
      "type": "Специальная карта",
      "abilities": "Мороз",
      "fraction": "Общий",
      "count": 3
    },
    {
      "name": "Ясное небо",
      "description": "Дромил, солнце-то светит! Значит и надежда есть...",
      "type": "Специальная карта",
      "abilities": "Ясное небо",
      "fraction": "Общий",
      "count": 3
    }
  ],
  "squad": [
    {
      "name": "Чучело",
      "description": "Пусть стреляют по крестьянам. А нет крестьян - поставьте чучела.",
      "type": "Специальная карта",
      "zone": "Ближний бой / Дальний бой / Осадные",
      "strength": 0,
      "hero": "Нет",
      "abilities": "Чучело",
      "fraction": "Общий",
      "count": 3
    },
    {
      "name": "Геральт из Ривии",
      "description": "Если нужно выбирать между одним злом и другим, я предпочитаю не выбирать вовсе.",
      "type": "Карта отрядов",
      "zone": "Ближний бой",
      "strength": 15,
      "hero": "Да",
      "abilities": "Нет",
      "fraction": "Общий",
      "count": 1
    },
    {
      "name": "Цирилла",
      "description": "Знаешь, когда сказки перестают быть сказками? Когда в них начинают верить.",
      "type": "Карта отрядов",
      "zone": "Ближний бой",
      "strength": 15,
      "hero": "Да",
      "abilities": "Нет",
      "fraction": "Общий",
      "count": 1
    },
    {
      "name": "Большой огненный скорпион",
      "description": "В зеррикании все такое огромное?",
      "type": "Карта отрядов",
      "zone": "Осадные",
      "strength": 10,
      "hero": "Нет",
      "abilities": "Нет",
      "fraction": "Нильфгаард",
      "count": 1
    },
    {
      "name": "Лето из Гулеты",
      "description": "Еще ни один ведьмак не умер от старости, в постели, диктуя завещание",
      "type": "Карта отрядов",
      "zone": "Ближний бой",
      "strength": 10,
      "hero": "Да",
      "abilities": "Нет",
      "fraction": "Нильфгаард",
      "count": 1
    },
    {
      "name": "Лучник Черной Пехоты",
      "description": "Я всегда бью по коленям.",
      "type": "Карта отрядов",
      "zone": "Дальний бой",
      "strength": 10,
      "hero": "Нет",
      "abilities": "Нет",
      "fraction": "Нильфгаард",
      "count": 2
    },
    {
      "name": "Менно Коегоорн",
      "description": "Но я вас отыщу, погодите, я вас научу заниматься разведкой!",
      "type": "Карта отрядов",
      "zone": "Ближний бой",
      "strength": 10,
      "hero": "Да",
      "abilities": "Медик",
      "fraction": "Нильфгаард",
      "count": 1
    },
    {
      "name": "Морван Воорхис",
      "description": "- А ты кто? Цирюльник?\n- Нет. Морван Воорхис. Командующий дивизией \"Альба\"",
      "type": "Карта отрядов",
      "zone": "Осадные",
      "strength": 10,
      "hero": "Да",
      "abilities": "Нет",
      "fraction": "Нильфгаард",
      "count": 1
    },
    {
      "name": "Тибор Эггебрахт",
      "description": "Вперед, \"Альба\"! Да здравствует император!",
      "type": "Карта отрядов",
      "zone": "Дальний бой",
      "strength": 10,
      "hero": "Да",
      "abilities": "Нет",
      "fraction": "Нильфгаард",
      "count": 1
    },
    {
      "name": "Стефан Скеллен",
      "description": "Шрам на лице нашей будущей императрицы - мое величайшее достижение.",
      "type": "Карта отрядов",
      "zone": "Ближний бой",
      "strength": 9,
      "hero": "Нет",
      "abilities": "Шпион",
      "fraction": "Нильфгаард",
      "count": 1
    },
    {
      "name": "Приманенный бес",
      "description": "Рррр!",
      "type": "Карта отрядов",
      "zone": "Ближний бой",
      "strength": 8,
      "hero": "Нет",
      "abilities": "Приманка приманка",
      "fraction": "Общий",
      "count": 1
    },
    {
      "name": "Виллентретенмерт",
      "description": "Дракон ушел от удара мягким, ловким, полным грации поворотом.",
      "type": "Карта отрядов",
      "zone": "Ближний бой",
      "strength": 7,
      "hero": "Нет",
      "abilities": "Казнь",
      "fraction": "Общий",
      "count": 1
    },
    {
      "name": "Йенннифер из Венгерберга",
      "description": "Одетая в черное и белое, она напоминала декабрьский рассвет.",
      "type": "Карта отрядов",
      "zone": "Дальний бой",
      "strength": 7,
      "hero": "Да",
      "abilities": "Медик",
      "fraction": "Общий",
      "count": 1
    },
    {
      "name": "Трисс Меригольд",
      "description": "Я могу о себе позаботиться. Поверь.",
      "type": "Карта отрядов",
      "zone": "Ближний бой",
      "strength": 7,
      "hero": "Да",
      "abilities": "Нет",
      "fraction": "Общий",
      "count": 1
    },
    {
      "name": "Шилярд Фиц-Остерлен",
      "description": "Война - это только кровь и вопли. Ход истории определяет дипломатия.",
      "type": "Карта отрядов",
      "zone": "Ближний бой",
      "strength": 7,
      "hero": "Нет",
      "abilities": "Шпион",
      "fraction": "Нильфгаард",
      "count": 1
    },
    {
      "name": "Ассире вар Анагыд",
      "description": "У нильфгаардских чародеев всесгда есть выбор: служба имератору - или эшафот.",
      "type": "Карта отрядов",
      "zone": "Дальний бой",
      "strength": 6,
      "hero": "Нет",
      "abilities": "Нет",
      "fraction": "Нильфгаард",
      "count": 1
    },
    {
      "name": "Весемир",
      "description": "Перед казнью попроси воды. Кто знает, что случится, пока ее принесут.",
      "type": "Карта отрядов",
      "zone": "Ближний бой",
      "strength": 6,
      "hero": "Нет",
      "abilities": "Нет",
      "fraction": "Общий",
      "count": 1
    },
    {
      "name": "Кагыр Маур аэп Каеллах",
      "description": "Разыскивается за убийство, дезертирство, воровство и подделку документов...",
      "type": "Карта отрядов",
      "zone": "Ближний бой",
      "strength": 6,
      "hero": "Нет",
      "abilities": "Нет",
      "fraction": "Нильфгаард",
      "count": 1
    },
    {
      "name": "Ольгерд фон Эверек",
      "description": "Теперь ты, по крайней мере знает, что мне не так легко потерять голову.",
      "type": "Карта отрядов",
      "zone": "Ближний бой / Дальний бой",
      "strength": 6,
      "hero": "Нет",
      "abilities": "Прилив Сил",
      "fraction": "Общий",
      "count": 1
    },
    {
      "name": "Сапер",
      "description": "В умелых руках простой отвес может стать смертельным оружием.",
      "type": "Карта отрядов",
      "zone": "Осадные",
      "strength": 6,
      "hero": "Нет",
      "abilities": "Нет",
      "fraction": "Нильфгаард",
      "count": 1
    },
    {
      "name": "Фрингилья Виго",
      "description": "Ослепление - подходящая кара для чародеек. Оно уязвляет их тщеславие.",
      "type": "Карта отрядов",
      "zone": "Дальний бой",
      "strength": 6,
      "hero": "Нет",
      "abilities": "Нет",
      "fraction": "Нильфгаард",
      "count": 1
    },
    {
      "name": "Молодой посланник",
      "description": "Шпион - громко сказано. Я, скорее, наблюдатель.",
      "type": "Карта отрядов",
      "zone": "Ближний бой",
      "strength": 5,
      "hero": "Нет",
      "abilities": "Прочная связь",
      "fraction": "Нильфгаард",
      "count": 2
    },
    {
      "name": "Огненный скорпион",
      "description": "Зеррикания славится своими скорпионами",
      "type": "Карта отрядов",
      "zone": "Осадные",
      "strength": 5,
      "hero": "Нет",
      "abilities": "Нет",
      "fraction": "Нильфгаард",
      "count": 1
    },
    {
      "name": "Ренуальд аэп Матсен",
      "description": "Гвардейцы бригады \"Импера\" не боятся никого... Кроме Ренуальда аэп Матсена.",
      "type": "Карта отрядов",
      "zone": "Дальний бой",
      "strength": 5,
      "hero": "Нет",
      "abilities": "Нет",
      "fraction": "Нильфгаард",
      "count": 1
    },
    {
      "name": "Золтан Хивай",
      "description": "Говорят, краснолюд ради товарища на виселицу пойдет. Золтан - не исключение.",
      "type": "Карта отрядов",
      "zone": "Ближний бой",
      "strength": 5,
      "hero": "Нет",
      "abilities": "Нет",
      "fraction": "Общий",
      "count": 1
    },
    {
      "name": "Эмиель Регис",
      "description": "Я, деликатно говоря, считаюсь чудовищем. Кровожадным монстром.",
      "type": "Карта отрядов",
      "zone": "Ближний бой",
      "strength": 5,
      "hero": "Нет",
      "abilities": "Нет",
      "fraction": "Общий",
      "count": 1
    },
    {
      "name": "Вангемар",
      "description": "Я люблю играть с огнем. С нордлингами эта игра особенно интересна.",
      "type": "Карта отрядов",
      "zone": "Дальний бой",
      "strength": 4,
      "hero": "Нет",
      "abilities": "Нет",
      "fraction": "Нильфгаард",
      "count": 1
    },
    {
      "name": "Ватье де Ридо",
      "description": "Нет такой проблемы, какой не решило бы хорошо спланированное убийство.",
      "type": "Карта отрядов",
      "zone": "Ближний бой",
      "strength": 4,
      "hero": "Нет",
      "abilities": "Шпион",
      "fraction": "Нильфгаард",
      "count": 1
    },
    {
      "name": "Гюнтер О'Димм: тьма",
      "description": "Бойся не темноты, а света.",
      "type": "Карта отрядов",
      "zone": "Дальний бой",
      "strength": 4,
      "hero": "Нет",
      "abilities": "Двойник",
      "fraction": "Общий",
      "count": 3,
      "aspect": "Гюнтер О'Димм: тьма"
    },
    {
      "name": "Раинфарн",
      "description": "- Этот Раинфарн, он когда-нибудь улыбается?\nУгу, когда кого-нибудь убьет.",
      "type": "Карта отрядов",
      "zone": "Ближний бой",
      "strength": 4,
      "hero": "Нет",
      "abilities": "Нет",
      "fraction": "Нильфгаард",
      "count": 1
    },
    {
      "name": "Цинтия",
      "description": "Цинтия очень талантлива. Ее нужно держать на коротком поводке.",
      "type": "Карта отрядов",
      "zone": "Дальний бой",
      "strength": 4,
      "hero": "Нет",
      "abilities": "Нет",
      "fraction": "Нильфгаард",
      "count": 1
    },
    {
      "name": "Бригада \"Импера\"",
      "description": "\"Импера\" будет драться до последнего бойца.",
      "type": "Карта отрядов",
      "zone": "Ближний бой",
      "strength": 3,
      "hero": "Нет",
      "abilities": "Прочная связь",
      "fraction": "Нильфгаард",
      "count": 4
    },
    {
      "name": "Мортейзен",
      "description": "Конники рванулись, рубя, давя и полосуя.",
      "type": "Карта отрядов",
      "zone": "Ближний бой",
      "strength": 3,
      "hero": "Нет",
      "abilities": "Нет",
      "fraction": "Нильфгаард",
      "count": 1
    },
    {
      "name": "Путткаммер",
      "description": "Кадет Путткаммер! Вы не писатель-беллетрист! Вы - будущий офицер!",
      "type": "Карта отрядов",
      "zone": "Дальний бой",
      "strength": 3,
      "hero": "Нет",
      "abilities": "Нет",
      "fraction": "Нильфгаард",
      "count": 1
    },
    {
      "name": "Сгнившая петрария",
      "description": "Запах гнилья навеевает на меня воспоминания о детстве.",
      "type": "Карта отрядов",
      "zone": "Осадные",
      "strength": 3,
      "hero": "Нет",
      "abilities": "Нет",
      "fraction": "Нильфгаард",
      "count": 1
    },
    {
      "name": "Альбрых",
      "description": "Огненный шар? Как пожелаете!",
      "type": "Карта отрядов",
      "zone": "Дальний бой",
      "strength": 2,
      "hero": "Нет",
      "abilities": "Нет",
      "fraction": "Нильфгаард",
      "count": 1
    },
    {
      "name": "Вреемде",
      "description": "Вреемде славился своим упрямством. И жестокостью.",
      "type": "Карта отрядов",
      "zone": "Ближний бой",
      "strength": 2,
      "hero": "Нет",
      "abilities": "Нет",
      "fraction": "Нильфгаард",
      "count": 1
    },
    {
      "name": "Кавалерия \"Наузиикаа\"",
      "description": "- Это Дикая Охота?\n- Нет. Это кавалерийская бригада \"Наузикаа\"",
      "type": "Карта отрядов",
      "zone": "Ближний бой",
      "strength": 2,
      "hero": "Нет",
      "abilities": "Прочная связь",
      "fraction": "Нильфгаард",
      "count": 3
    },
    {
      "name": "Лютик",
      "description": "Ты циник, свинтус, бабник и лжец. И поверь, ничего сложного в тебе нет.",
      "type": "Карта отрядов",
      "zone": "Ближний бой",
      "strength": 2,
      "hero": "Нет",
      "abilities": "Командирский рог",
      "fraction": "Общий",
      "count": 1
    },
    {
      "name": "Свирс",
      "description": "За работу, сукины дети!",
      "type": "Карта отрядов",
      "zone": "Дальний бой",
      "strength": 2,
      "hero": "Нет",
      "abilities": "Нет",
      "fraction": "Нильфгаард",
      "count": 1
    },
    {
      "name": "Гюнтер О'Димм",
      "description": "- Он всегда дает именно то, чего ты хочешь. И в этом проблема",
      "type": "Карта отрядов",
      "zone": "Осадные",
      "strength": 2,
      "hero": "Нет",
      "abilities": "Двойник",
      "fraction": "Общий",
      "count": 1,
      "aspect": "Гюнтер О'Димм"
    },
    {
      "name": "Лучная поддержка",
      "description": "Бей в глаз, не порти шкурку!",
      "type": "Карта отрядов",
      "zone": "Дальний бой",
      "strength": 1,
      "hero": "Нет",
      "abilities": "Медик",
      "fraction": "Нильфгаард",
      "count": 2
    },
    {
      "name": "Аваллакх",
      "description": "У вас, людей... странные вкусы.",
      "type": "Карта отрядов",
      "zone": "Ближний бой",
      "strength": 0,
      "hero": "Да",
      "abilities": "Шпион",
      "fraction": "Общий",
      "count": 1
    },
    {
      "name": "Осадная поддержка",
      "description": "Я дважды не промахиваюсь.",
      "type": "Карта отрядов",
      "zone": "Осадные",
      "strength": 0,
      "hero": "Нет",
      "abilities": "Медик",
      "fraction": "Нильфгаард",
      "count": 1
    },
    {
      "name": "Приманка",
      "description": "Муу!",
      "type": "Карта отрядов",
      "zone": "Ближний бой",
      "strength": 0,
      "hero": "Нет",
      "abilities": "Приманка",
      "fraction": "Общий",
      "count": 1
    }
  ]
}
